evergreen_fft/__init__.py
evergreen_fft/_evergreen_fft.so
evergreen_fft/evergreen_fft.py
evergreen_fft-1.0.11.dist-info/LICENSE
evergreen_fft-1.0.11.dist-info/METADATA
evergreen_fft-1.0.11.dist-info/WHEEL
evergreen_fft-1.0.11.dist-info/top_level.txt
evergreen_fft-1.0.11.dist-info/RECORD
