Metadata-Version: 2.1
Name: evergreen-fft
Version: 1.0.11
Summary: A python fft package based on evergreenforest
Home-page: UNKNOWN
Author: Rice
Author-email: mrseanrice@gmail.com
License: UNKNOWN
Platform: UNKNOWN
Classifier: Programming Language :: Python :: 2.7
Classifier: License :: OSI Approved :: MIT License
